pyramid_bpython.py
pyramid_bpython-0.1.dist-info/DESCRIPTION.rst
pyramid_bpython-0.1.dist-info/entry_points.txt
pyramid_bpython-0.1.dist-info/METADATA
pyramid_bpython-0.1.dist-info/metadata.json
pyramid_bpython-0.1.dist-info/RECORD
pyramid_bpython-0.1.dist-info/top_level.txt
pyramid_bpython-0.1.dist-info/WHEEL
